README.rst
VERSION
requirements.txt
nglimsclient/__init__.py
nglimsclient-0.2.1.dist-info/DESCRIPTION.rst
nglimsclient-0.2.1.dist-info/METADATA
nglimsclient-0.2.1.dist-info/RECORD
nglimsclient-0.2.1.dist-info/WHEEL
nglimsclient-0.2.1.dist-info/metadata.json
nglimsclient-0.2.1.dist-info/top_level.txt
nglimsclient-0.2.1.dist-info/zip-safe
