Metadata-Version: 2.0
Name: nglimsclient
Version: 0.2.1
Summary: nglims client package for bioblend
Home-page: https://bitbucket.org/crs4/nglimsclient
Author: Gianmauro Cuccuru,Luca Lianas,Luca Pireddu,Rossano Atzeni
Author-email: <gmauro@crs4.it>,<lianas@crs4.it>,<pireddu@crs4.it>,<ratzeni@crs4.it>
License: MIT
Keywords: utilities
Platform: Posix; MacOS X; Windows
Classifier: Development Status :: 4 - Beta
Classifier: Intended Audience :: Developers
Classifier: License :: OSI Approved :: MIT License
Classifier: Operating System :: OS Independent
Classifier: Topic :: Internet
Classifier: Programming Language :: Python :: 2.7
Requires-Dist: bioblend
